{
  "name": "Centaur Warrunner",
  "primary_attribute": "strength",
  "roles": [
    "nuker",
    "initiator",
    "durable",
    "disabler"
  ],
  "tags": [
    "melee",
    "initiator",
    "durable",
    "global",
    "reflect",
    "burst_damage"
  ],
  "positions": {
    "pos_1": 2.9,
    "pos_2": 3.2,
    "pos_3": 83.5,
    "pos_4": 7.1,
    "pos_5": 3.3
  },
  "game_phase": {
    "early": 6,
    "mid": 9,
    "late": 7
  },
  "explicit_counters": {
    "Meepo": -6.44,
    "Lifestealer": -5.12,
    "Dazzle": -4.56,
    "Clinkz": -4.42,
    "Wraith King": -3.84,
    "Bounty Hunter": -3.73,
    "Enigma": -3.35,
    "Slardar": -3.29,
    "Witch Doctor": -2.84,
    "Omniknight": -2.76
  },
  "explicit_synergies": {
    "Meepo": 7.06,
    "Batrider": 5.63,
    "Bloodseeker": 5.52,
    "Primal Beast": 4.49,
    "Enchantress": 3.77,
    "Slardar": 2.6,
    "Naga Siren": 2.4,
    "Death Prophet": 2.26,
    "Ember Spirit": 2.05,
    "Lone Druid": 1.92
  }
}