{
  "name": "Dark Willow",
  "primary_attribute": "intelligence",
  "roles": [
    "nuker",
    "disabler",
    "support"
  ],
  "tags": [
    "ranged",
    "disable_heavy",
    "burst_damage",
    "escape",
    "nuker"
  ],
  "positions": {
    "pos_1": 4.7,
    "pos_2": 13.2,
    "pos_3": 5.8,
    "pos_4": 38.5,
    "pos_5": 37.8
  },
  "game_phase": {
    "early": 6,
    "mid": 9,
    "late": 8
  },
  "explicit_counters": {
    "Omniknight": -7.56,
    "Lycan": -7.22,
    "Naga Siren": -7.14,
    "Meepo": -6.73,
    "Troll Warlord": -6.25,
    "Spectre": -5.78,
    "Legion Commander": -5.35,
    "Wraith King": -5.19,
    "Enigma": -5.19,
    "Venomancer": -5.08
  },
  "explicit_synergies": {
    "Naga Siren": 9.37,
    "Elder Titan": 6.61,
    "Treant Protector": 5.65,
    "Troll Warlord": 4.04,
    "Meepo": 3.33,
    "Shadow Shaman": 2.55,
    "Dark Seer": 2.45,
    "Windranger": 2.43,
    "Leshrac": 2.34,
    "Puck": 2.28
  }
}